tv_report
