Metadata-Version: 1.1
Name: tv-report
Version: 1.1.5
Summary: A parser for tv show episode files of various formats
Home-page: https://github.com/justin8/tv_report
Author: Justin Dray
Author-email: justin@dray.be
License: MIT
Platform: UNKNOWN
Classifier: Operating System :: OS Independent
Classifier: Programming Language :: Python :: 3 :: Only
Classifier: Programming Language :: Python :: 3
Classifier: Environment :: Console
Classifier: License :: OSI Approved :: MIT License
Classifier: Development Status :: 5 - Production/Stable
Classifier: Programming Language :: Python
